xiaobai_id_validator/__init__.py
xiaobai_id_validator/data.py
xiaobai_id_validator/func.py
xiaobai_id_validator/helper.py
xiaobai_id_validator/utils.py
xiaobai_id_validator/validator.py
xiaobai_id_validator-1.0.1.dist-info/METADATA
xiaobai_id_validator-1.0.1.dist-info/WHEEL
xiaobai_id_validator-1.0.1.dist-info/top_level.txt
xiaobai_id_validator-1.0.1.dist-info/RECORD
